{
  "wall-climb": {
    "_skill_name": "攀",
    "技能类型": "位移技能",
    "移动速度": "≤7.15米/秒",
    "持续时间": "≤1.04秒"
  },
  "lunge": {
    "_skill_name": "跃",
    "冷却时间": "4秒",
    "移动速度": "水平初速度15米/秒",
    "移动距离": "7.85米"
  },
  "storm-bow": {
    "_skill_name": "风",
    "子弹类型": "延迟弹道有下坠",
    "下坠速度": "重力加速度=g",
    "蓄力时间": "0~0.72秒",
    "弹匣容量": "无限",
    "能否暴击": "爆头时为暴击（2倍）"
  },
  "sonic-arrow": {
    "_skill_name": "音",
    "冷却时间": "12秒",
    "子弹类型": "延迟弹道有下坠",
    "探测范围": "球体，半径9米",
    "存在时间": "6秒",
    "能否暴击": "爆头时暴击（2倍）"
  },
  "storm-arrows": {
    "_skill_name": "岚",
    "冷却时间": "8秒，结束后计算冷却",
    "伤害量": "75点/支",
    "飞行速度": "140米/秒",
    "持续时间": "≤5秒，可取消，不可被打断",
    "箭矢数量": "≤5支，可取消，不可被打断",
    "攻击频率": "0.25秒/支=4支/秒",
    "能否暴击": "爆头时暴击（2倍）"
  },
  "dragon-strike": {
    "_skill_name": "竜",
    "技能类型": "范围伤害",
    "移动速度": "禁用方向键，但保留速度",
    "飞行速度": "15米/秒",
    "伤害量": "125点",
    "前摇": "0.9秒",
    "后摇": "0.6秒",
    "能否暴击": "不可暴击",
    "所需充能": "1700点",
    "飞行距离": "无限",
    "伤害范围": "圆柱体，半径4米，长待测量"
  },
  "frost-arrow": {
    "_skill_name": "霜冻之箭",
    "冷却时间": "14秒",
    "溅射范围": "球体半径4米"
  }
}